{"items":{"layers":{"82401363":{"id":82401363,"name":"new 2d graphics","clearColor":"000000","clearAlpha":1,"shouldUseClearRect":true,"zIndex":1,"pixelRatio":720,"defaultConfig":[{"title":"Settings","items":{"clearColor":{"type":"String","value":"000000","tooltip":"Color of the background when clearing, not used when shouldUseClearRect is checked"},"clearAlpha":{"type":"Number","value":1,"tooltip":"Alpha of the background when clearing, not used when shouldUseClearRect is checked"},"shouldUseClearRect":{"type":"Boolean","value":true,"tooltip":"Clears the entire canvas, more performant than using a clear color"},"zIndex":{"type":"Number","value":1,"tooltip":"Position of this layer relative to other layers"},"pixelRatio":{"type":"Number","value":720,"min":1,"max":2048,"tooltip":"resolution of the canvas the items are drawn to, uses an automatic aspect ratio"},"scalePixelRatioOnExport":{"type":"Boolean","value":true,"tooltip":"Scales the pixelRatio on export in case it doesn't match the output value, this will make the video look different when exporting"}}}],"items":[585683,4045800,4485615],"width":640,"height":480,"passes":[],"layerType":2}},"passes":[],"items":{"82401363":{"585683":{"defaultConfig":[{"title":"Author Information","hide":true,"items":{"author":{"value":"example","type":"String","disabled":false},"website":{"value":"http://example.org","type":"Link","disabled":false},"github":{"value":"https://github.com/example","type":"Link","disabled":false}}},{"title":"Base Configurations","items":{"start":{"value":0,"type":"Number","tooltip":"Time in seconds when item will be rendered","disableAutomations":true},"duration":{"value":20,"type":"Number","tooltip":"Time in seconds when item won't be rendered anymore","disableAutomations":true},"zIndex":{"value":0,"type":"Number","tooltip":"Index of turn in renderloop","disableAutomations":true}}},{"title":"Settings","items":{"color":{"type":"String","value":"EEE"},"x":{"type":"Number","value":0},"y":{"type":"Number","value":0},"height":{"type":"Number","value":1},"width":{"type":"Number","value":1}}}],"id":585683,"offsetLeft":0,"name":"SQUARE","movable":true,"sceneId":82401363,"automations":[],"itemType":"SQUARE","author":"example","website":"http://example.org","github":"https://github.com/example","start":0,"duration":253.5,"zIndex":0,"color":"EEE","x":0,"y":0,"height":1,"width":1,"index":0},"4045800":{"defaultConfig":[{"title":"Author Information","hide":true,"items":{"author":{"value":"example","type":"String","disabled":false},"website":{"value":"http://example.org","type":"Link","disabled":false},"github":{"value":"https://github.com/example","type":"Link","disabled":false}}},{"title":"Base Configurations","items":{"start":{"value":0,"type":"Number","tooltip":"Time in seconds when item will be rendered","disableAutomations":true},"duration":{"value":20,"type":"Number","tooltip":"Time in seconds when item won't be rendered anymore","disableAutomations":true},"zIndex":{"value":1,"type":"Number","tooltip":"Index of turn in renderloop","disableAutomations":true}}},{"title":"Settings","items":{"useFFTBins":{"type":"Boolean","value":false},"amplitude":{"type":"Number","value":25},"capacity":{"type":"Number","value":1000},"distance":{"type":"Number","value":0.1},"extent":{"type":"Number","value":0.25},"x":{"type":"Number","value":0},"y":{"type":"Number","value":3.5},"z":{"type":"Number","value":0},"scale":{"type":"Number","value":1},"songDuration":{"type":"Number","value":180}}},{"title":"Colors","items":{"shiftingColors":{"type":"Boolean","value":true},"shiftSpeed":{"type":"Number","value":0.1},"shiftingDarkness":{"type":"Number","value":90,"tooltip":"Upper bound for shifting color values"},"red":{"type":"Number","value":225,"disabled":false},"blue":{"type":"Number","value":225,"disabled":false},"green":{"type":"Number","value":225,"disabled":false},"alpha":{"type":"Number","value":0.2}}},{"title":"Glow","items":{"glow":{"type":"Boolean","value":false},"shiftingGlowColors":{"type":"Boolean","value":false},"shadowColor":{"type":"String","value":"FFFFFF"},"shadowBlur":{"type":"Number","value":20},"shadowOffsetX":{"type":"Number","value":0},"shadowOffsetY":{"type":"Number","value":0}}}],"id":4045800,"offsetLeft":0,"name":"POLARTONE","movable":true,"sceneId":82401363,"automations":[],"itemType":"POLARTONE","author":"example","website":"http://example.org","github":"https://github.com/example","start":0,"duration":255.25,"zIndex":1,"useFFTBins":false,"amplitude":25,"capacity":1000,"distance":0.1,"extent":0.25,"x":0,"y":"3","z":0,"scale":1,"songDuration":180,"shiftingColors":false,"shiftSpeed":0.1,"shiftingDarkness":90,"red":"0","blue":"0","green":"0","alpha":0.2,"glow":false,"shiftingGlowColors":false,"shadowColor":"FFFFFF","shadowBlur":20,"shadowOffsetX":0,"shadowOffsetY":0,"index":0,"items":["red","blue","green"],"disabled":false,"groupIndex":3},"4485615":{"defaultConfig":[{"title":"Author Information","hide":true,"items":{"author":{"value":"example","type":"String","disabled":false},"website":{"value":"http://example.org","type":"Link","disabled":false},"github":{"value":"https://github.com/example","type":"Link","disabled":false}}},{"title":"Base Configurations","items":{"start":{"value":0,"type":"Number","tooltip":"Time in seconds when item will be rendered","disableAutomations":true},"duration":{"value":20,"type":"Number","tooltip":"Time in seconds when item won't be rendered anymore","disableAutomations":true},"zIndex":{"value":2,"type":"Number","tooltip":"Index of turn in renderloop","disableAutomations":true}}},{"title":"Text settings","items":{"text":{"type":"String","value":"Text"},"fontSize":{"type":"Number","value":80},"baseLine":{"type":"List","options":["middle","bottom","top"],"value":"middle"},"font":{"type":"List","options":["Andale Mono","Arial Italic","Comic Sans MS","sans-serif","Courier New Bold","Arial","Impact","Tahoma","Verdana Bold","Lucida Sans Bold"],"defaultIndex":0,"value":"Andele Mono"},"textAlign":{"type":"List","options":["center","left","right"],"value":"center","defaultIndex":0},"x":{"type":"Number","value":0.5},"y":{"type":"Number","value":0.5},"color":{"type":"String","value":"FFFFFF"}}}],"id":4485615,"offsetLeft":0,"name":"title","movable":true,"sceneId":82401363,"automations":[],"itemType":"TEXT","author":"example","website":"http://example.org","github":"https://github.com/example","start":0,"duration":252.5,"zIndex":2,"text":"Artist-Track","fontSize":"40","baseLine":"middle","font":"Andele Mono","textAlign":"center","x":0.5,"y":"0.04","color":"3333","index":1}}},"automations":{"585683":[],"4045800":[],"4485615":[]},"cameras":{},"controls":{},"fog":{},"settings":{},"audioInfo":{"defaultConfig":[{"title":"Author Information","hide":true,"items":{"author":{"value":"example","type":"String","disabled":false},"website":{"value":"http://example.org","type":"Link","disabled":false},"github":{"value":"https://github.com/example","type":"Link","disabled":false}}},{"title":"Base Configurations","items":{"start":{"value":0,"type":"Number","tooltip":"Time in seconds when item will be rendered","disableAutomations":true,"disabled":true},"duration":{"value":20,"type":"Number","tooltip":"Time in seconds when item won't be rendered anymore","disableAutomations":true,"disabled":true},"zIndex":{"type":"Number","tooltip":"Index of turn in renderloop","disableAutomations":true}}},{"title":"Audio Info","items":{"sampleRate":{"value":0,"type":"Number","tooltip":"","disabled":true},"channels":{"value":0,"type":"Number","tooltip":"","disabled":true},"volume":{"value":100,"type":"Number","tooltip":"Volume","min":0,"max":100}}}],"id":3746450,"offsetLeft":0,"name":"SG Lewis - No Less (Kartell Remix) w Lyrics.mp3","movable":true,"automations":[],"itemType":"SOUND","author":"example","website":"http://example.org","github":"https://github.com/example","start":0,"duration":252.99591666666666,"type":"SOUND","sampleRate":48000,"channels":2,"volume":100,"maxDuration":252.99591666666666},"sideBarWindowIndex":2,"selectedItemId":4045800,"selectedLayerId":82401363,"audioItems":[{"defaultConfig":[{"title":"Author Information","hide":true,"items":{"author":{"value":"example","type":"String","disabled":false},"website":{"value":"http://example.org","type":"Link","disabled":false},"github":{"value":"https://github.com/example","type":"Link","disabled":false}}},{"title":"Base Configurations","items":{"start":{"value":0,"type":"Number","tooltip":"Time in seconds when item will be rendered","disableAutomations":true,"disabled":true},"duration":{"value":20,"type":"Number","tooltip":"Time in seconds when item won't be rendered anymore","disableAutomations":true,"disabled":true},"zIndex":{"type":"Number","tooltip":"Index of turn in renderloop","disableAutomations":true}}},{"title":"Audio Info","items":{"sampleRate":{"value":0,"type":"Number","tooltip":"","disabled":true},"channels":{"value":0,"type":"Number","tooltip":"","disabled":true},"volume":{"value":100,"type":"Number","tooltip":"Volume","min":0,"max":100}}}],"id":3746450,"offsetLeft":0,"name":"Audio","movable":true,"automations":[],"itemType":"SOUND","author":"example","website":"http://example.org","github":"https://github.com/example","start":0,"duration":252.99591666666666,"type":"SOUND","sampleRate":48000,"channels":2,"volume":100,"maxDuration":252.99591666666666,"index":0}],"createEffect":null,"itemIdx":1,"audioIDx":0,"audioItemView":1,"effectId":7235132,"initialized":false,"loadFromFile":false,"audioIdx":0},"globals":{"time":108.42209999999614,"clipDuration":300,"fps":60,"playing":true,"frameId":6505,"disabled":false,"encoding":false,"fftSettings":{},"audioBufferSize":0.1,"postProcessingEnabled":false,"masterVolume":100,"exportVideo":false,"fftSize":"2048","lastAction":"SET_TIME"}}